glsapi/__init__.py
glsapi/classes/__init__.py
glsapi/classes/api.py
glsapi/classes/http.py
glsapi-0.9.1.dist-info/METADATA
glsapi-0.9.1.dist-info/WHEEL
glsapi-0.9.1.dist-info/licenses/LICENSE
glsapi-0.9.1.dist-info/RECORD
