Metadata-Version: 2.1
Name: glsapi
Version: 0.9.1
Summary: Simple Python wrapper to fetch data from GLS (gls-group.eu)
Project-URL: Homepage, https://kumig.it/kumitterer/glsapi
Project-URL: Bug Tracker, https://kumig.it/kumitterer/glsapi/issues
Author-email: Kumi Mitterer <glsapi@kumi.email>
License: Copyright (c) 2023 Kumi Mitterer <glsapi@kumi.email>
License-File: LICENSE
Classifier: License :: OSI Approved :: MIT License
Classifier: Operating System :: OS Independent
Classifier: Programming Language :: Python :: 3
Requires-Python: >=3.10
